hypos.py
hypos-0.0.3.dist-info/LICENSE.md
hypos-0.0.3.dist-info/METADATA
hypos-0.0.3.dist-info/WHEEL
hypos-0.0.3.dist-info/top_level.txt
hypos-0.0.3.dist-info/RECORD
