Metadata-Version: 2.1
Name: hypos
Version: 0.0.3
Summary: PrABpY
Home-page: https://github.com/PrABpY/ML-Hypothesis.git
Author: prabdalip
Author-email: anasterstudio@gmail.com
License: MIT
Classifier: Programming Language :: Python :: 3
Classifier: License :: OSI Approved :: MIT License
Classifier: Development Status :: 3 - Alpha
License-File: LICENSE.md
Requires-Dist: numpy
